LICENSE
MANIFEST.in
README.md
setup.py
deeplearing_tools.egg-info/PKG-INFO
deeplearing_tools.egg-info/SOURCES.txt
deeplearing_tools.egg-info/dependency_links.txt
deeplearing_tools.egg-info/requires.txt
deeplearing_tools.egg-info/top_level.txt
deeplearning_tools/__init__.py
deeplearning_tools/backbone/__init__.py
deeplearning_tools/backbone/mbv3.py
deeplearning_tools/backbone/resnet.py
deeplearning_tools/cnn/__init__.py
deeplearning_tools/cnn/train.py
deeplearning_tools/cnn/val.py
deeplearning_tools/dataset/__init__.py
deeplearning_tools/dataset/detection.py
deeplearning_tools/dataset/filename.py
deeplearning_tools/module/__init__.py
deeplearning_tools/module/general.py
deeplearning_tools/networks/__init__.py
deeplearning_tools/networks/centernet/__init__.py
deeplearning_tools/networks/centernet/dataset.py
deeplearning_tools/networks/centernet/loss.py
deeplearning_tools/networks/centernet/model.py
deeplearning_tools/utils/__init__.py
deeplearning_tools/utils/box.py
deeplearning_tools/utils/encode.py
deeplearning_tools/utils/env.py
deeplearning_tools/utils/image.py
deeplearning_tools/utils/label_map.py
deeplearning_tools/utils/timer.py
mypackage/__init__.py
mypackage/__version__.py
mypackage/core.py