Metadata-Version: 2.1
Name: deeplearing-tools
Version: 0.1.2
Summary: About to learn deeplearing tools.
Home-page: https://github.com/me/myproject
Author: some one
Author-email: 546162357@qq.com
License: MIT
Platform: UNKNOWN
Classifier: License :: OSI Approved :: MIT License
Classifier: Programming Language :: Python
Classifier: Programming Language :: Python :: 3
Classifier: Programming Language :: Python :: 3.6
Classifier: Programming Language :: Python :: Implementation :: CPython
Classifier: Programming Language :: Python :: Implementation :: PyPy
Requires-Python: >=3.6.0
